auroris/__init__.py
auroris/_version.py
auroris/cli.py
auroris/types.py
auroris/utils.py
auroris/curation/__init__.py
auroris/curation/_curator.py
auroris/curation/functional.py
auroris/curation/actions/__init__.py
auroris/curation/actions/_ac_stereoisomer.py
auroris/curation/actions/_base.py
auroris/curation/actions/_deduplicate.py
auroris/curation/actions/_discretize.py
auroris/curation/actions/_distribution.py
auroris/curation/actions/_mol.py
auroris/curation/actions/_outlier.py
auroris/report/__init__.py
auroris/report/_report.py
auroris/report/broadcaster/__init__.py
auroris/report/broadcaster/_base.py
auroris/report/broadcaster/_html.py
auroris/report/broadcaster/_logger.py
auroris/report/broadcaster/templates/report.html.jinja
auroris/visualization/__init__.py
auroris/visualization/_chemspace.py
auroris/visualization/_distribution.py
auroris/visualization/utils.py
auroris-0.1.9.dist-info/LICENSE
auroris-0.1.9.dist-info/METADATA
auroris-0.1.9.dist-info/NOTICE
auroris-0.1.9.dist-info/WHEEL
auroris-0.1.9.dist-info/entry_points.txt
auroris-0.1.9.dist-info/top_level.txt
auroris-0.1.9.dist-info/RECORD
