Metadata-Version: 2.1
Name: auroris
Version: 0.1.9
Summary: Data Curation in Polaris
Author-email: Lu Zhu <lu@valencediscovery.com>, Julien St-Laurent <julien.stl@valencediscovery.com>, Cas Wognum <cas@valencediscovery.com>
Project-URL: Website, https://polarishub.io/
Project-URL: Source Code, https://github.com/polaris-hub/auroris
Project-URL: Bug Tracker, https://github.com/polaris-hub/auroris/issues
Project-URL: Documentation, https://polaris-hub.github.io/auroris/
Classifier: Development Status :: 3 - Alpha
Classifier: Intended Audience :: Developers
Classifier: Intended Audience :: Healthcare Industry
Classifier: Intended Audience :: Science/Research
Classifier: Topic :: Scientific/Engineering :: Artificial Intelligence
Classifier: Topic :: Scientific/Engineering :: Bio-Informatics
Classifier: Topic :: Scientific/Engineering :: Information Analysis
Classifier: Topic :: Scientific/Engineering :: Medical Science Apps.
Classifier: Natural Language :: English
Classifier: Operating System :: OS Independent
Classifier: Programming Language :: Python
Classifier: Programming Language :: Python :: 3
Classifier: Programming Language :: Python :: 3.10
Classifier: Programming Language :: Python :: 3.11
Classifier: Programming Language :: Python :: 3.12
Requires-Python: >=3.10
License-File: LICENSE
License-File: NOTICE
Requires-Dist: tqdm
Requires-Dist: loguru
Requires-Dist: typer
Requires-Dist: pydantic>=2
Requires-Dist: numpy
Requires-Dist: pandas<2.2.0
Requires-Dist: scipy
Requires-Dist: scikit-learn
Requires-Dist: matplotlib
Requires-Dist: seaborn
Requires-Dist: datamol>=0.12.1
Requires-Dist: rdkit
Requires-Dist: pillow
Requires-Dist: fsspec
Requires-Dist: pyarrow
Provides-Extra: dev
Requires-Dist: pytest; extra == "dev"
Requires-Dist: pytest-xdist; extra == "dev"
Requires-Dist: pytest-cov; extra == "dev"
Requires-Dist: ruff; extra == "dev"
Requires-Dist: jupyterlab; extra == "dev"
Requires-Dist: ipywidgets; extra == "dev"
Provides-Extra: doc
Requires-Dist: mkdocs; extra == "doc"
Requires-Dist: mkdocs-material>=9.4.7; extra == "doc"
Requires-Dist: mkdocstrings; extra == "doc"
Requires-Dist: mkdocstrings-python; extra == "doc"
Requires-Dist: mkdocs-jupyter; extra == "doc"
Requires-Dist: markdown-include; extra == "doc"
Requires-Dist: mdx-truly-sane-lists; extra == "doc"
Requires-Dist: nbconvert; extra == "doc"
Requires-Dist: mike>=1.0.0; extra == "doc"
